{
  "schema": 1,
  "packs": [
    {
      "pack_id": "c3599ba17efd5faeed6bd1c954a9fbf97dd72f2417911fe27a79e5ffa139f410",
      "created_by": "Joshabracks",
      "created_at_unix": 1784667593,
      "message_count": 8,
      "workspace": "Joshabracks/society-4-alpha"
    },
    {
      "pack_id": "a5382a8d4d845657cfdeb8bd0c1896a0290898fa4eb58328baadbfdfb26f2e7c",
      "created_by": "Joshabracks",
      "created_at_unix": 1784667589,
      "message_count": 8,
      "workspace": "Joshabracks/society-4-alpha"
    },
    {
      "pack_id": "0224a8571285590796aee8fa0033a2f3ef1b5144044774e1cb9faebc0690068f",
      "created_by": "Joshabracks",
      "created_at_unix": 1784667581,
      "message_count": 8,
      "workspace": "Joshabracks/society-4-alpha"
    },
    {
      "pack_id": "d5376d90a12a52db01e2af9e327b6068799781ee3bbbe58b57fbf735efdefeea",
      "created_by": "Joshabracks",
      "created_at_unix": 1784667573,
      "message_count": 8,
      "workspace": "Joshabracks/society-4-alpha"
    },
    {
      "pack_id": "dcc8d0933e3b906bfd7387933780bf30119f9774141acd7f67bd100085915d7c",
      "created_by": "Joshabracks",
      "created_at_unix": 1784667566,
      "message_count": 8,
      "workspace": "Joshabracks/society-4-alpha"
    },
    {
      "pack_id": "c1c4425ca53558413baa3739a4ea25244dc5f4b6361745e040e08ce339aacf9e",
      "created_by": "Joshabracks",
      "created_at_unix": 1784667557,
      "message_count": 8,
      "workspace": "Joshabracks/society-4-alpha"
    },
    {
      "pack_id": "36ef9dcd0a7f8e02d9593ce06d281e5c26922cc6527d1f4b31c3ec759f747239",
      "created_by": "Joshabracks",
      "created_at_unix": 1784667553,
      "message_count": 8,
      "workspace": "Joshabracks/society-4-alpha"
    }
  ]
}